CHANGES.md
MANIFEST.in
README.md
setup.py
kort/__init__.py
kort/api.py
kort/conf.py
kort/models.py
kort.egg-info/PKG-INFO
kort.egg-info/SOURCES.txt
kort.egg-info/dependency_links.txt
kort.egg-info/entry_points.txt
kort.egg-info/requires.txt
kort.egg-info/top_level.txt
kort/bin/__init__.py
kort/bin/api.py
kort/bin/cli.py
kort/bin/wsgi.py
kort/helpers/__init__.py
kort/helpers/algo.py
kort/helpers/sqla.py